refurb_json_minify/__init__.py
refurb_json_minify/common.py
refurb_json_minify/dont_dump_integers.py
refurb_json_minify/use_json_separators.py
refurb_json_minify-1.0.0.dist-info/entry_points.txt
refurb_json_minify-1.0.0.dist-info/LICENSE
refurb_json_minify-1.0.0.dist-info/WHEEL
refurb_json_minify-1.0.0.dist-info/METADATA
refurb_json_minify-1.0.0.dist-info/RECORD
