Metadata-Version: 2.1
Name: refurb-json-minify
Version: 1.0.0
Summary: Detects places where JSON output can be minified
Home-page: https://github.com/dosisod/refurb-json-minify
License: GPL-3.0-only
Author: dosisod
Classifier: Development Status :: 4 - Beta
Classifier: Environment :: Console
Classifier: Intended Audience :: Developers
Classifier: License :: OSI Approved :: GNU General Public License v3 (GPLv3)
Classifier: Programming Language :: Python :: 2
Classifier: Programming Language :: Python :: 2.7
Classifier: Programming Language :: Python :: 3
Classifier: Programming Language :: Python :: 3.10
Classifier: Programming Language :: Python :: 3.4
Classifier: Programming Language :: Python :: 3.5
Classifier: Programming Language :: Python :: 3.6
Classifier: Programming Language :: Python :: 3.7
Classifier: Programming Language :: Python :: 3.8
Classifier: Programming Language :: Python :: 3.9
Classifier: Topic :: Software Development :: Testing
Classifier: Typing :: Typed
Requires-Dist: refurb (>=1.4)
Project-URL: Repository, https://github.com/dosisod/refurb-json-minify
